{
    "1871": {
        "due_deligences": [
            {
                "capitalRatio": 39,
                "date": "2019-06-19",
                "isError": false,
                "underpriced": 30.0,
                "valueParShare": 1768
            }
        ],
        "filerName": "株式会社ピーエス三菱",
        "stockPrice": 536
    },
    "1967": {
        "due_deligences": [
            {
                "capitalRatio": 71,
                "date": "2019-06-19",
                "isError": false,
                "underpriced": 34.0,
                "valueParShare": 1930
            }
        ],
        "filerName": "株式会社ヤマト",
        "stockPrice": 656
    },
    "2175": {
        "due_deligences": [
            {
                "capitalRatio": 33,
                "date": "2019-06-19",
                "isError": false,
                "underpriced": 553.0,
                "valueParShare": 384
            }
        ],
        "filerName": "株式会社エス・エム・エス",
        "stockPrice": 2124
    },
    "2196": {
        "due_deligences": [
            {
                "capitalRatio": 29,
                "date": "2019-06-19",
                "isError": false,
                "underpriced": 30.0,
                "valueParShare": 1166
            }
        ],
        "filerName": "株式会社エスクリ",
        "stockPrice": 346
    },
    "2468": {
        "due_deligences": [
            {
                "capitalRatio": 66,
                "date": "2019-06-19",
                "isError": false,
                "underpriced": 365.0,
                "valueParShare": 84
            }
        ],
        "filerName": "株式会社フュートレック",
        "stockPrice": 307
    },
    "2760": {
        "due_deligences": [
            {
                "capitalRatio": 34,
                "date": "2019-06-19",
                "isError": false,
                "underpriced": 50.0,
                "valueParShare": 4567
            }
        ],
        "filerName": "東京エレクトロンデバイス株式会社",
        "stockPrice": 2297
    },
    "2767": {
        "due_deligences": [
            {
                "capitalRatio": 51,
                "date": "2019-06-19",
                "isError": false,
                "underpriced": -77.0,
                "valueParShare": -405
            }
        ],
        "filerName": "フィールズ株式会社",
        "stockPrice": 312
    },
    "2883": {
        "due_deligences": [
            {
                "isError": true
            }
        ],
        "filerName": "株式会社大冷",
        "stockPrice": 1836
    },
    "3178": {
        "due_deligences": [
            {
                "capitalRatio": 62,
                "date": "2019-06-19",
                "isError": false,
                "underpriced": 89.0,
                "valueParShare": 1715
            }
        ],
        "filerName": "チムニー株式会社",
        "stockPrice": 1527
    },
    "3258": {
        "due_deligences": [
            {
                "capitalRatio": 16,
                "date": "2019-06-19",
                "isError": false,
                "underpriced": -74.0,
                "valueParShare": -8097
            }
        ],
        "filerName": "ユニゾホールディングス株式会社",
        "stockPrice": 5970
    },
    "3352": {
        "due_deligences": [
            {
                "isError": true
            }
        ],
        "filerName": "株式会社バッファロー",
        "stockPrice": 1079
    },
    "3738": {
        "due_deligences": [
            {
                "capitalRatio": 26,
                "date": "2019-06-19",
                "isError": false,
                "underpriced": 101.0,
                "valueParShare": 2058
            }
        ],
        "filerName": "株式会社ティーガイア",
        "stockPrice": 2077
    },
    "3850": {
        "due_deligences": [
            {
                "capitalRatio": 64,
                "date": "2019-06-19",
                "isError": false,
                "underpriced": 182.0,
                "valueParShare": 1851
            }
        ],
        "filerName": "株式会社エヌ・ティ・ティ・データ・イントラマート",
        "stockPrice": 3365
    },
    "3932": {
        "due_deligences": [
            {
                "capitalRatio": 63,
                "date": "2019-06-19",
                "isError": false,
                "underpriced": 36.0,
                "valueParShare": 10184
            }
        ],
        "filerName": "株式会社アカツキ",
        "stockPrice": 3645
    },
    "3936": {
        "due_deligences": [
            {
                "isError": true
            }
        ],
        "filerName": "株式会社グローバルウェイ",
        "stockPrice": 1045
    },
    "3956": {
        "due_deligences": [
            {
                "isError": true
            }
        ],
        "filerName": "国際チャート株式会社",
        "stockPrice": 232
    },
    "4345": {
        "due_deligences": [
            {
                "capitalRatio": 59,
                "date": "2019-06-19",
                "isError": false,
                "underpriced": 126.0,
                "valueParShare": 429
            }
        ],
        "filerName": "株式会社シーティーエス",
        "stockPrice": 542
    },
    "4548": {
        "due_deligences": [
            {
                "capitalRatio": 91,
                "date": "2019-06-19",
                "isError": false,
                "underpriced": 98.0,
                "valueParShare": 1121
            }
        ],
        "filerName": "生化学工業株式会社",
        "stockPrice": 1098
    },
    "4679": {
        "due_deligences": [
            {
                "isError": true
            }
        ],
        "filerName": "株式会社　田　谷",
        "stockPrice": 570
    },
    "4732": {
        "due_deligences": [
            {
                "capitalRatio": 79,
                "date": "2019-06-19",
                "isError": false,
                "underpriced": 131.0,
                "valueParShare": 1259
            }
        ],
        "filerName": "株式会社ユー・エス・エス",
        "stockPrice": 1643
    },
    "4820": {
        "due_deligences": [
            {
                "capitalRatio": 74,
                "date": "2019-06-19",
                "isError": false,
                "underpriced": 81.0,
                "valueParShare": 1110
            }
        ],
        "filerName": "株式会社イーエムシステムズ（商号　株式会社ＥＭシステムズ）",
        "stockPrice": 896
    },
    "4902": {
        "due_deligences": [
            {
                "isError": true
            }
        ],
        "filerName": "コニカミノルタ株式会社",
        "stockPrice": 389
    },
    "4968": {
        "due_deligences": [
            {
                "capitalRatio": 61,
                "date": "2019-06-19",
                "isError": false,
                "underpriced": 36.0,
                "valueParShare": 3263
            }
        ],
        "filerName": "荒川化学工業株式会社",
        "stockPrice": 1171
    },
    "4999": {
        "due_deligences": [
            {
                "capitalRatio": 54,
                "date": "2019-06-19",
                "isError": false,
                "underpriced": 56.0,
                "valueParShare": 1166
            }
        ],
        "filerName": "セメダイン株式会社",
        "stockPrice": 655
    },
    "5280": {
        "due_deligences": [
            {
                "capitalRatio": 55,
                "date": "2019-06-19",
                "isError": false,
                "underpriced": 15.0,
                "valueParShare": 5083
            }
        ],
        "filerName": "ヨシコン株式会社",
        "stockPrice": 773
    },
    "5852": {
        "due_deligences": [
            {
                "capitalRatio": 48,
                "date": "2019-06-19",
                "isError": false,
                "underpriced": 73.0,
                "valueParShare": 470
            }
        ],
        "filerName": "株式会社アーレスティ",
        "stockPrice": 344
    },
    "5857": {
        "due_deligences": [
            {
                "isError": true
            }
        ],
        "filerName": "アサヒホールディングス株式会社",
        "stockPrice": 2219
    },
    "5933": {
        "due_deligences": [
            {
                "capitalRatio": 49,
                "date": "2019-06-19",
                "isError": false,
                "underpriced": 56.0,
                "valueParShare": 1651
            }
        ],
        "filerName": "アルインコ株式会社",
        "stockPrice": 918
    },
    "6089": {
        "due_deligences": [
            {
                "isError": true
            }
        ],
        "filerName": "株式会社ウィルグループ",
        "stockPrice": 576
    },
    "6161": {
        "due_deligences": [
            {
                "capitalRatio": 83,
                "date": "2019-06-19",
                "isError": false,
                "underpriced": 56.0,
                "valueParShare": 6650
            }
        ],
        "filerName": "株式会社エスティック",
        "stockPrice": 3725
    },
    "6501": {
        "due_deligences": [
            {
                "isError": true
            }
        ],
        "filerName": "株式会社日立製作所",
        "stockPrice": 3167
    },
    "6584": {
        "due_deligences": [
            {
                "capitalRatio": 34,
                "date": "2019-06-19",
                "isError": false,
                "underpriced": 109.0,
                "valueParShare": 650
            }
        ],
        "filerName": "三櫻工業株式会社",
        "stockPrice": 707
    },
    "6594": {
        "due_deligences": [
            {
                "isError": true
            }
        ],
        "filerName": "日本電産株式会社",
        "stockPrice": 5591
    },
    "6641": {
        "due_deligences": [
            {
                "capitalRatio": 68,
                "date": "2019-06-19",
                "isError": false,
                "underpriced": 42.0,
                "valueParShare": 2145
            }
        ],
        "filerName": "日新電機株式会社",
        "stockPrice": 898
    },
    "6645": {
        "due_deligences": [
            {
                "isError": true
            }
        ],
        "filerName": "オムロン株式会社",
        "stockPrice": 5820
    },
    "6740": {
        "due_deligences": [
            {
                "capitalRatio": 1,
                "date": "2019-06-19",
                "isError": false,
                "underpriced": -5.0,
                "valueParShare": -908
            }
        ],
        "filerName": "株式会社ジャパンディスプレイ",
        "stockPrice": 49
    },
    "6788": {
        "due_deligences": [
            {
                "capitalRatio": 77,
                "date": "2019-06-19",
                "isError": false,
                "underpriced": 78.0,
                "valueParShare": 3691
            }
        ],
        "filerName": "株式会社日本トリム",
        "stockPrice": 2893
    },
    "7205": {
        "due_deligences": [
            {
                "capitalRatio": 44,
                "date": "2019-06-19",
                "isError": false,
                "underpriced": 40.0,
                "valueParShare": 1472
            }
        ],
        "filerName": "日野自動車株式会社",
        "stockPrice": 582
    },
    "7241": {
        "due_deligences": [
            {
                "capitalRatio": 30,
                "date": "2019-06-19",
                "isError": false,
                "underpriced": 169.0,
                "valueParShare": 270
            }
        ],
        "filerName": "フタバ産業株式会社",
        "stockPrice": 456
    },
    "7259": {
        "due_deligences": [
            {
                "isError": true
            }
        ],
        "filerName": "アイシン精機株式会社",
        "stockPrice": 2769
    },
    "7267": {
        "due_deligences": [
            {
                "isError": true
            }
        ],
        "filerName": "本田技研工業株式会社",
        "stockPrice": 2418
    },
    "7504": {
        "due_deligences": [
            {
                "capitalRatio": 56,
                "date": "2019-06-19",
                "isError": false,
                "underpriced": 67.0,
                "valueParShare": 1787
            }
        ],
        "filerName": "株式会社高速",
        "stockPrice": 1203
    },
    "7908": {
        "due_deligences": [
            {
                "capitalRatio": 77,
                "date": "2019-06-19",
                "isError": false,
                "underpriced": 44.0,
                "valueParShare": 294
            }
        ],
        "filerName": "株式会社きもと",
        "stockPrice": 129
    },
    "7931": {
        "due_deligences": [
            {
                "capitalRatio": 81,
                "date": "2019-06-19",
                "isError": false,
                "underpriced": 65.0,
                "valueParShare": 3013
            }
        ],
        "filerName": "未来工業株式会社",
        "stockPrice": 1944
    },
    "7971": {
        "due_deligences": [
            {
                "capitalRatio": 46,
                "date": "2019-06-19",
                "isError": false,
                "underpriced": 47.0,
                "valueParShare": 535
            }
        ],
        "filerName": "東リ株式会社",
        "stockPrice": 251
    },
    "8014": {
        "due_deligences": [
            {
                "capitalRatio": 45,
                "date": "2019-06-19",
                "isError": false,
                "underpriced": 32.0,
                "valueParShare": 4460
            }
        ],
        "filerName": "蝶理株式会社",
        "stockPrice": 1406
    },
    "8038": {
        "due_deligences": [
            {
                "capitalRatio": 54,
                "date": "2019-06-19",
                "isError": false,
                "underpriced": 58.0,
                "valueParShare": 4599
            }
        ],
        "filerName": "東都水産株式会社",
        "stockPrice": 2652
    },
    "8081": {
        "due_deligences": [
            {
                "capitalRatio": 50,
                "date": "2019-06-19",
                "isError": false,
                "underpriced": 47.0,
                "valueParShare": 2458
            }
        ],
        "filerName": "株式会社カナデン",
        "stockPrice": 1145
    },
    "8133": {
        "due_deligences": [
            {
                "isError": true
            }
        ],
        "filerName": "伊藤忠エネクス株式会社",
        "stockPrice": 828
    },
    "8361": {
        "due_deligences": [
            {
                "isError": true
            }
        ],
        "filerName": "株式会社　大垣共立銀行",
        "stockPrice": 2071
    },
    "8595": {
        "due_deligences": [
            {
                "capitalRatio": 89,
                "date": "2019-06-19",
                "isError": false,
                "underpriced": 34.0,
                "valueParShare": 9052
            }
        ],
        "filerName": "株式会社ジャフコ",
        "stockPrice": 3055
    },
    "9045": {
        "due_deligences": [
            {
                "capitalRatio": 33,
                "date": "2019-06-19",
                "isError": false,
                "underpriced": 1173.0,
                "valueParShare": 407
            }
        ],
        "filerName": "京阪ホールディングス株式会社",
        "stockPrice": 4775
    },
    "9057": {
        "due_deligences": [
            {
                "capitalRatio": 55,
                "date": "2019-06-19",
                "isError": false,
                "underpriced": 148.0,
                "valueParShare": 1587
            }
        ],
        "filerName": "遠州トラック株式会社",
        "stockPrice": 2341
    },
    "9086": {
        "due_deligences": [
            {
                "isError": true
            }
        ],
        "filerName": "株式会社日立物流",
        "stockPrice": 2379
    },
    "9101": {
        "due_deligences": [
            {
                "capitalRatio": 26,
                "date": "2019-06-19",
                "isError": false,
                "underpriced": -74.0,
                "valueParShare": -1874
            }
        ],
        "filerName": "日本郵船株式会社",
        "stockPrice": 1379
    },
    "9201": {
        "due_deligences": [
            {
                "capitalRatio": 59,
                "date": "2019-06-19",
                "isError": false,
                "underpriced": 38.0,
                "valueParShare": 5275
            }
        ],
        "filerName": "日本航空株式会社",
        "stockPrice": 2014
    },
    "9375": {
        "due_deligences": [
            {
                "capitalRatio": 34,
                "date": "2019-06-19",
                "isError": false,
                "underpriced": 82.0,
                "valueParShare": 1919
            }
        ],
        "filerName": "株式会社近鉄エクスプレス",
        "stockPrice": 1573
    },
    "9437": {
        "due_deligences": [
            {
                "isError": true
            }
        ],
        "filerName": "株式会社ＮＴＴドコモ",
        "stockPrice": 3288
    },
    "9445": {
        "due_deligences": [
            {
                "capitalRatio": 23,
                "date": "2019-06-19",
                "isError": false,
                "underpriced": 57.0,
                "valueParShare": 474
            }
        ],
        "filerName": "株式会社フォーバルテレコム",
        "stockPrice": 271
    },
    "9640": {
        "due_deligences": [
            {
                "capitalRatio": 63,
                "date": "2019-06-19",
                "isError": false,
                "underpriced": 69.0,
                "valueParShare": 2460
            }
        ],
        "filerName": "株式会社セゾン情報システムズ",
        "stockPrice": 1696
    },
    "9726": {
        "due_deligences": [
            {
                "capitalRatio": 19,
                "date": "2019-06-19",
                "isError": false,
                "underpriced": 77.0,
                "valueParShare": 1081
            }
        ],
        "filerName": "ＫＮＴ－ＣＴホールディングス株式会社",
        "stockPrice": 828
    },
    "9909": {
        "due_deligences": [
            {
                "isError": true
            }
        ],
        "filerName": "愛光電気株式会社",
        "stockPrice": 1602
    },
    "9984": {
        "due_deligences": [
            {
                "isError": true
            }
        ],
        "filerName": "ソフトバンクグループ株式会社",
        "stockPrice": 4183
    }
}